drxtract/Makefile
drxtract/__init__.py
drxtract/bitd2bmp.py
drxtract/casxtract.py
drxtract/clut2json.py
drxtract/drxtract.py
drxtract/fmapxtract.py
drxtract/lscr2js.py
drxtract/lscr2lingo.py
drxtract/riffxtract.py
drxtract/rte22bmp.py
drxtract/snd2wav.py
drxtract/stxt2json.py
drxtract/vwlbxtract.py
drxtract/vwscxtract.py
drxtract/bitd/__init__.py
drxtract/bitd/bitd2bmp.py
drxtract/bitd/decoder.py
drxtract/bitd/decoder16b.py
drxtract/bitd/decoder24b.py
drxtract/bitd/decoder2b.py
drxtract/bitd/decoder4b.py
drxtract/bitd/decoder8b.py
drxtract/cas/__init__.py
drxtract/cas/cas.py
drxtract/cast/__init__.py
drxtract/cast/button.py
drxtract/cast/cast.py
drxtract/cast/castparser.py
drxtract/cast/image.py
drxtract/cast/palette.py
drxtract/cast/script.py
drxtract/cast/shape.py
drxtract/cast/sound.py
drxtract/cast/text.py
drxtract/cast/textinput.py
drxtract/cast/transition.py
drxtract/clut/__init__.py
drxtract/clut/clut.py
drxtract/common/__init__.py
drxtract/common/constants.py
drxtract/dir/__init__.py
drxtract/dir/dir.py
drxtract/fmap/__init__.py
drxtract/fmap/fmap.py
drxtract/key/__init__.py
drxtract/key/key.py
drxtract/lctx/__init__.py
drxtract/lctx/lctx.py
drxtract/lingosrc/__init__.py
drxtract/lingosrc/util.py
drxtract/lingosrc/ast/__init__.py
drxtract/lingosrc/ast/constant_val.py
drxtract/lingosrc/ast/conversion.py
drxtract/lingosrc/ast/function_op.py
drxtract/lingosrc/ast/node.py
drxtract/lingosrc/ast/operation.py
drxtract/lingosrc/ast/script.py
drxtract/lingosrc/ast/structures.py
drxtract/lingosrc/ast/variable.py
drxtract/lingosrc/ast/win_tell.py
drxtract/lingosrc/codegen/__init__.py
drxtract/lingosrc/codegen/js.py
drxtract/lingosrc/codegen/lingo.py
drxtract/lingosrc/model/__init__.py
drxtract/lingosrc/model/context.py
drxtract/lingosrc/model/header.py
drxtract/lingosrc/opcodes/__init__.py
drxtract/lingosrc/opcodes/assign_op.py
drxtract/lingosrc/opcodes/binary_op.py
drxtract/lingosrc/opcodes/call_op.py
drxtract/lingosrc/opcodes/constant_op.py
drxtract-0.1.4.dist-info/METADATA
drxtract-0.1.4.dist-info/WHEEL
drxtract-0.1.4.dist-info/entry_points.txt
drxtract-0.1.4.dist-info/licenses/LICENSE
drxtract-0.1.4.dist-info/RECORD
