Metadata-Version: 2.3
Name: drxtract
Version: 0.1.4
Summary: Macromedia/Adobe DIR and DRX extraction package
Project-URL: Homepage, https://github.com/System25/drxtract
Project-URL: Bug Tracker, https://github.com/System25/drxtract/issues
Author-email: Abraham Macias Paredes <system252001@yahoo.es>
License-File: LICENSE
Classifier: License :: OSI Approved :: GNU General Public License v2 (GPLv2)
Classifier: Operating System :: OS Independent
Classifier: Programming Language :: Python :: 3
Requires-Python: >=3.10.6
Provides-Extra: tests
Requires-Dist: parameterized>=0.8.1; extra == 'tests'
Requires-Dist: pytest>=6.2.5; extra == 'tests'
